_quickder.cpython-36m-darwin.so
pyquickder-1.2.2.data/scripts/asn1literate
pyquickder-1.2.2.data/scripts/asn2quickder
pyquickder-1.2.2.dist-info/DESCRIPTION.rst
pyquickder-1.2.2.dist-info/METADATA
pyquickder-1.2.2.dist-info/RECORD
pyquickder-1.2.2.dist-info/WHEEL
pyquickder-1.2.2.dist-info/metadata.json
pyquickder-1.2.2.dist-info/top_level.txt
quick_der/__init__.py
quick_der/api.py
quick_der/builder.py
quick_der/classes.py
quick_der/format.py
quick_der/main.py
quick_der/packstx.py
quick_der/primitive.py
tests/__init__.py
tests/test01.py
tests/test01a.py
tests/test02.py
tests/test04.py
tests/test_asn2quickder.py
